ebltable/__init__.py
ebltable/ebl_from_model.py
ebltable/interpolate.py
ebltable/tau_from_model.py
ebltable/data/CUBA_UVB.dat
ebltable/data/EBL_nuInu_model_A_Finke2022.dat
ebltable/data/EBL_proper_baseline.dat
ebltable/data/EBL_proper_low_pop3.dat
ebltable/data/EBL_proper_up_pop3.dat
ebltable/data/EBL_z_0_baseline.dat
ebltable/data/EBL_z_0_low_pop3.dat
ebltable/data/EBL_z_0_up_pop3.dat
ebltable/data/ebl_dominguez.dat
ebltable/data/ebl_dominguez11.out
ebltable/data/ebl_franceschini.dat
ebltable/data/ebl_lower_uncertainties_dominguez11.out
ebltable/data/ebl_modelC_Finke.txt
ebltable/data/ebl_nuFnu_tanja.dat
ebltable/data/ebl_saldana21_comoving.txt
ebltable/data/ebl_upper_uncertainties_dominguez11.out
ebltable/data/eblerr_saldana21_comoving.txt
ebltable/data/eblflux_fiducial.dat
ebltable/data/eblflux_fixed.dat
ebltable/data/nuInu_kneiske.dat
ebltable/data/opdep_fiducial.dat
ebltable/data/opdep_fixed.dat
ebltable/data/tau_dominguez10.dat
ebltable/data/tau_dominguez11_cta.out
ebltable/data/tau_ebl_cmb_kneiske.dat
ebltable/data/tau_ebl_cmb_kneiske_bestfit.dat
ebltable/data/tau_fran08.dat
ebltable/data/tau_fran17.dat
ebltable/data/tau_gg_baseline.dat
ebltable/data/tau_gg_low_pop3.dat
ebltable/data/tau_gg_up_pop3.dat
ebltable/data/tau_high_saldana-lopez21.out
ebltable/data/tau_low_saldana-lopez21.out
ebltable/data/tau_lower_dominguez11_cta.out
ebltable/data/tau_modelC_Finke.txt
ebltable/data/tau_model_A_Finke2022.dat
ebltable/data/tau_saldana-lopez21.out
ebltable/data/tau_upper_dominguez11_cta.out
tests/__init__.py
tests/test_ebl.py
tests/test_opt_depth.py
ebltable-0.6.3.dist-info/LICENSE
ebltable-0.6.3.dist-info/METADATA
ebltable-0.6.3.dist-info/WHEEL
ebltable-0.6.3.dist-info/top_level.txt
ebltable-0.6.3.dist-info/RECORD
