Metadata-Version: 2.1
Name: ebltable
Version: 0.6.3
Summary: Python code to read in and interpolate tables for absorption of high energy gamma rays with additional helper functions
Home-page: https://github.com/me-manu/ebltable
Author: Manuel Meyer
Author-email: me.manu@gmx.net
License: BSD
Keywords: extragalactic backgroun light,Fermi,IACT,EBL,gamma-ray,absorption,opacity,LIV,Lorentz invariance violation
Classifier: Development Status :: 4 - Beta
Classifier: Intended Audience :: Science/Research
Classifier: Topic :: Scientific/Engineering :: Astronomy
Classifier: License :: OSI Approved :: BSD License
Classifier: Programming Language :: Python :: 3.6
Classifier: Programming Language :: Python :: 3.7
License-File: LICENSE
Requires-Dist: numpy >=1.19
Requires-Dist: scipy >=1.5
Requires-Dist: astropy >=4.0
